Vaishu/__init__.py
Vaishu-0.0.1.dist-info/LICENSE.txt
Vaishu-0.0.1.dist-info/METADATA
Vaishu-0.0.1.dist-info/WHEEL
Vaishu-0.0.1.dist-info/top_level.txt
Vaishu-0.0.1.dist-info/RECORD
